scda_dash_auth/__init__.py
scda_dash_auth/assets/authInterceptor.js
scda_dash_auth/scda_auth.py
scda_dash_auth/utils.py
scda_dash_auth-0.3.8.dist-info/LICENSE
scda_dash_auth-0.3.8.dist-info/METADATA
scda_dash_auth-0.3.8.dist-info/WHEEL
scda_dash_auth-0.3.8.dist-info/RECORD
