Metadata-Version: 2.3
Name: scda-dash-auth
Version: 0.3.8
Summary: wrapper for scda dash authentication qdt auth service and Microsoft Identity Platform
Author: Cesar Flores
Author-email: cesar@qdt.ai
Requires-Python: >=3.9
Classifier: License :: OSI Approved :: MIT License
Classifier: Operating System :: OS Independent
Classifier: Programming Language :: Python :: 3
Classifier: Programming Language :: Python :: 3.9
Classifier: Programming Language :: Python :: 3.10
Classifier: Programming Language :: Python :: 3.11
Classifier: Programming Language :: Python :: 3.12
Classifier: Programming Language :: Python :: 3.13
Requires-Dist: dash-auth (>=2.3.0,<3.0.0)
